beta_code/__init__.py
beta_code/beta_code.py
beta_code/vendor/beta-code-json/beta_code_to_unicode.json
beta_code/vendor/beta-code-json/unicode_to_beta_code.json
beta_code-1.1.1.dist-info/LICENSE
beta_code-1.1.1.dist-info/METADATA
beta_code-1.1.1.dist-info/WHEEL
beta_code-1.1.1.dist-info/top_level.txt
beta_code-1.1.1.dist-info/RECORD
