Metadata-Version: 2.1
Name: beta-code
Version: 1.1.1
Summary: Converts Greek Beta Code to Greek characters and vice versa
Home-page: https://github.com/perseids-tools/beta-code-py
Author: perseids
Author-email: perseids@tufts.edu
License: UNKNOWN
Platform: UNKNOWN
Classifier: Programming Language :: Python
Classifier: License :: OSI Approved :: MIT License
Classifier: Operating System :: OS Independent
